{
 "aggregate_function_based_on": "cost_of_equipment__rs_in_lakhs",
 "color": "#ECAD4B",
 "creation": "2024-06-11 16:32:42.036502",
 "docstatus": 0,
 "doctype": "Number Card",
 "document_type": "R and D facilities",
 "dynamic_filters_json": "[]",
 "filters_json": "[]",
 "function": "Sum",
 "idx": 0,
 "is_public": 1,
 "is_standard": 1,
 "label": "Total worth of all R&D equipment's ( in Lakhs )",
 "modified": "2024-06-11 16:32:47.967102",
 "modified_by": "Administrator",
 "module": "RDCC",
 "name": "Total worth of all R&D equipment's ( in Lakhs )",
 "owner": "Administrator",
 "parent_document_type": "",
 "report_function": "Sum",
 "show_percentage_stats": 1,
 "stats_time_interval": "Daily",
 "type": "Document Type"
}